<?xml version="1.0" ?>
<Commentary away_team_name="Southampton" competition="English Premier League" game_date="2013-09-15 16:00" game_id_2="27060267" game_id_4="110807691" home_team_name="West Ham" lang_id="en" season="Season 2013/2014" season_id="2013" sport_id="1" sport_name="Football">
	<message comment="Second half ends" last_modified="2013-09-15 17:34:10" minute="94" period="2" second="2" team="West Ham" time="97" type="end" type_id="30"/>
	<message comment="Victor Wanyama misses attempt (To the left, Out of box, Left footed, Open play)" last_modified="2013-09-15 17:33:41" minute="93" period="2" second="33" team="West Ham" time="96" type="attempt missed" type_id="13"/>
	<message comment="Ricardo Vaz Tê wins a corner (To the left)" last_modified="2013-09-15 17:32:05" minute="91" period="2" second="57" team="Southampton" time="94" type="corner" type_id="6"/>
	<message comment="James Collins wins a corner (To the right)" last_modified="2013-09-15 17:31:33" minute="91" period="2" second="25" team="Southampton" time="94" type="corner" type_id="6"/>
	<message comment="Daniel Osvaldo wins a corner (To the left)" last_modified="2013-09-15 17:29:26" minute="89" period="2" second="18" team="West Ham" time="92" type="corner" type_id="6"/>
	<message comment="Rickie Lambert wins a corner (To the right)" last_modified="2013-09-15 17:29:03" minute="88" period="2" second="55" team="West Ham" time="91" type="corner" type_id="6"/>
	<message comment="James Collins misses attempt (High, 18-yard box, Right footed, Open play)" last_modified="2013-09-15 17:23:26" minute="83" period="2" second="18" team="Southampton" time="86" type="attempt missed" type_id="13"/>
	<message comment="Ricardo Vaz Tê wins a corner (To the right)" last_modified="2013-09-15 17:22:32" minute="82" period="2" second="24" team="Southampton" time="85" type="corner" type_id="6"/>
	<message comment="José Fonte misses attempt (To the left, 6-yard box, Left footed, Set piece)" last_modified="2013-09-15 17:18:40" minute="78" period="2" second="32" team="West Ham" time="81" type="attempt missed" type_id="13"/>
	<message comment="Ravel Morrison is substituted off" last_modified="2013-09-15 17:17:01" minute="76" period="2" second="53" team="Southampton" time="79" type="substitution off" type_id="18"/>
	<message comment="Matthew Taylor is substituted on" last_modified="2013-09-15 17:17:01" minute="76" period="2" second="53" team="Southampton" time="79" type="substitution on" type_id="19"/>
	<message comment="Luke Shaw is substituted off" last_modified="2013-09-15 17:16:48" minute="76" period="2" second="40" team="West Ham" time="79" type="substitution off" type_id="18"/>
	<message comment="Calum Chambers is substituted on" last_modified="2013-09-15 17:16:48" minute="76" period="2" second="40" team="West Ham" time="79" type="substitution on" type_id="19"/>
	<message comment="Rickie Lambert wins a corner (To the right)" last_modified="2013-09-15 17:11:57" minute="71" period="2" second="49" team="West Ham" time="74" type="corner" type_id="6"/>
	<message comment="Jussi Jääskeläinen makes a save (Diving, Parried safe)" last_modified="2013-09-15 17:11:55" minute="71" period="2" second="47" team="Southampton" time="74" type="save made" type_id="10"/>
	<message comment="Rickie Lambert has attempt saved (High to the right, 18-yard box, Right footed, Fast break)" last_modified="2013-09-15 17:11:55" minute="71" period="2" second="47" team="West Ham" time="74" type="attempt blocked" type_id="15"/>
	<message comment="Adam Lallana is substituted off" last_modified="2013-09-15 17:11:23" minute="71" period="2" second="15" team="West Ham" time="74" type="substitution off" type_id="18"/>
	<message comment="James Ward-Prowse is substituted on" last_modified="2013-09-15 17:11:23" minute="71" period="2" second="15" team="West Ham" time="74" type="substitution on" type_id="19"/>
	<message comment="Joey O'Brien recieves a yellow card" last_modified="2013-09-15 17:09:57" minute="69" period="2" second="49" team="Southampton" time="72" type="card received" type_id="17"/>
	<message comment="Modibo Maiga is substituted off" last_modified="2013-09-15 17:07:24" minute="67" period="2" second="16" team="Southampton" time="70" type="substitution off" type_id="18"/>
	<message comment="Ricardo Vaz Tê is substituted on" last_modified="2013-09-15 17:07:24" minute="67" period="2" second="16" team="Southampton" time="70" type="substitution on" type_id="19"/>
	<message comment="José Fonte misses attempt (18-yard box, Head, From corner)" last_modified="2013-09-15 17:06:51" minute="66" period="2" second="43" team="West Ham" time="69" type="attempt missed" type_id="13"/>
	<message comment="Morgan Schneiderlin wins a corner (To the right)" last_modified="2013-09-15 17:06:30" minute="66" period="2" second="22" team="West Ham" time="69" type="corner" type_id="6"/>
	<message comment="Jussi Jääskeläinen makes a save (Parried safe, Diving)" last_modified="2013-09-15 17:06:25" minute="66" period="2" second="17" team="Southampton" time="69" type="save made" type_id="10"/>
	<message comment="Morgan Schneiderlin has attempt saved (Low to the right, 18-yard box, Right footed, Open play)" last_modified="2013-09-15 17:06:25" minute="66" period="2" second="17" team="West Ham" time="69" type="attempt blocked" type_id="15"/>
	<message comment="Victor Wanyama recieves a yellow card" last_modified="2013-09-15 17:05:28" minute="65" period="2" second="20" team="West Ham" time="68" type="card received" type_id="17"/>
	<message comment="Mark Noble recieves a yellow card" last_modified="2013-09-15 17:03:22" minute="63" period="2" second="14" team="Southampton" time="66" type="card received" type_id="17"/>
	<message comment="Adam Lallana wins a corner (To the right)" last_modified="2013-09-15 17:01:35" minute="61" period="2" second="27" team="West Ham" time="64" type="corner" type_id="6"/>
	<message comment="Mohamed Diamé blocks a shot" last_modified="2013-09-15 17:01:26" minute="61" period="2" second="18" team="Southampton" time="64" type="save made" type_id="10"/>
	<message comment="Victor Wanyama has shot blocked (Out of box, Right footed, From corner)" last_modified="2013-09-15 17:01:26" minute="61" period="2" second="18" team="West Ham" time="64" type="attempt blocked" type_id="15"/>
	<message comment="Guy Demel is substituted off" last_modified="2013-09-15 17:01:08" minute="61" period="2" second="0" team="Southampton" time="64" type="substitution off" type_id="18"/>
	<message comment="Razvan Rat is substituted on" last_modified="2013-09-15 17:01:08" minute="61" period="2" second="0" team="Southampton" time="64" type="substitution on" type_id="19"/>
	<message comment="Morgan Schneiderlin wins a corner (To the right)" last_modified="2013-09-15 17:00:27" minute="60" period="2" second="19" team="West Ham" time="63" type="corner" type_id="6"/>
	<message comment="James Collins blocks a shot" last_modified="2013-09-15 17:00:25" minute="60" period="2" second="17" team="Southampton" time="63" type="save made" type_id="10"/>
	<message comment="Morgan Schneiderlin has shot blocked (18-yard box, Right footed, Open play)" last_modified="2013-09-15 17:00:25" minute="60" period="2" second="17" team="West Ham" time="63" type="attempt blocked" type_id="15"/>
	<message comment="Winston Reid blocks a shot" last_modified="2013-09-15 17:00:23" minute="60" period="2" second="15" team="Southampton" time="63" type="save made" type_id="10"/>
	<message comment="Daniel Osvaldo has shot blocked (18-yard box, Right footed, Open play)" last_modified="2013-09-15 17:00:23" minute="60" period="2" second="15" team="West Ham" time="63" type="attempt blocked" type_id="15"/>
	<message comment="Kevin Nolan is caught offside" last_modified="2013-09-15 16:55:08" minute="55" period="2" team="Southampton" time="58" type="offside" type_id="10000"/>
	<message comment="James Collins blocks a shot" last_modified="2013-09-15 16:48:57" minute="48" period="2" second="49" team="Southampton" time="51" type="save made" type_id="10"/>
	<message comment="Victor Wanyama has shot blocked (18-yard box, Right footed, From corner)" last_modified="2013-09-15 16:48:57" minute="48" period="2" second="49" team="West Ham" time="51" type="attempt blocked" type_id="15"/>
	<message comment="Rickie Lambert hits the woodwork (To the right, 18-yard box, Head, From corner)" last_modified="2013-09-15 16:48:55" minute="48" period="2" second="47" team="West Ham" time="51" type="woodwork hit" type_id="14"/>
	<message comment="Victor Wanyama wins a corner (To the right)" last_modified="2013-09-15 16:48:33" minute="48" period="2" second="25" team="West Ham" time="51" type="corner" type_id="6"/>
	<message comment="Jussi Jääskeläinen makes a save (Standing, Parried safe)" last_modified="2013-09-15 16:48:30" minute="48" period="2" second="22" team="Southampton" time="51" type="save made" type_id="10"/>
	<message comment="Victor Wanyama has attempt saved (High to the centre, Out of box, Right footed, Open play)" last_modified="2013-09-15 16:48:30" minute="48" period="2" second="22" team="West Ham" time="51" type="attempt blocked" type_id="15"/>
	<message comment="Second half begins!" last_modified="2013-09-15 16:45:08" minute="45" period="2" second="0" team="West Ham" time="48" type="start" type_id="32"/>
	<message comment="First half ends" last_modified="2013-09-15 16:47:12" minute="47" period="1" second="4" team="West Ham" time="47" type="end" type_id="30"/>
	<message comment="Modibo Maiga misses attempt (To the left, 18-yard box, Left footed, Open play)" last_modified="2013-09-15 16:46:15" minute="46" period="1" second="7" team="Southampton" time="46" type="attempt missed" type_id="13"/>
	<message comment="Victor Wanyama wins a corner (To the right)" last_modified="2013-09-15 16:42:24" minute="42" period="1" second="16" team="West Ham" time="42" type="corner" type_id="6"/>
	<message comment="Ravel Morrison misses attempt (Out of box, Right footed, Open play)" last_modified="2013-09-15 16:39:59" minute="39" period="1" second="51" team="Southampton" time="39" type="attempt missed" type_id="13"/>
	<message comment="Kevin Nolan misses attempt (18-yard box, Left footed, Open play)" last_modified="2013-09-15 16:39:56" minute="39" period="1" second="48" team="Southampton" time="39" type="attempt missed" type_id="13"/>
	<message comment="Rickie Lambert misses attempt (High, 18-yard box, Head, Set piece)" last_modified="2013-09-15 16:36:34" minute="36" period="1" second="26" team="West Ham" time="36" type="attempt missed" type_id="13"/>
	<message comment="Matthew Jarvis is caught offside" last_modified="2013-09-15 16:29:08" minute="29" period="1" team="Southampton" time="29" type="offside" type_id="10000"/>
	<message comment="Daniel Osvaldo wins a corner (To the right)" last_modified="2013-09-15 16:28:48" minute="28" period="1" second="40" team="West Ham" time="28" type="corner" type_id="6"/>
	<message comment="Mohamed Diamé recieves a yellow card" last_modified="2013-09-15 16:28:13" minute="28" period="1" second="5" team="Southampton" time="28" type="card received" type_id="17"/>
	<message comment="Matthew Jarvis wins a corner (To the left)" last_modified="2013-09-15 16:23:43" minute="23" period="1" second="35" team="Southampton" time="23" type="corner" type_id="6"/>
	<message comment="Jussi Jääskeläinen makes a save (Diving, Collected)" last_modified="2013-09-15 16:22:21" minute="22" period="1" second="13" team="Southampton" time="22" type="save made" type_id="10"/>
	<message comment="Rickie Lambert has attempt saved (Low to the left, 18-yard box, Right footed, Open play)" last_modified="2013-09-15 16:22:21" minute="22" period="1" second="13" team="West Ham" time="22" type="attempt blocked" type_id="15"/>
	<message comment="Mohamed Diamé misses attempt (Out of box, Right footed, Open play)" last_modified="2013-09-15 16:19:58" minute="19" period="1" second="50" team="Southampton" time="19" type="attempt missed" type_id="13"/>
	<message comment="Daniel Osvaldo wins a corner (To the left)" last_modified="2013-09-15 16:10:21" minute="10" period="1" second="13" team="West Ham" time="10" type="corner" type_id="6"/>
	<message comment="Jussi Jääskeläinen makes a save (Parried safe, Diving, Other body part)" last_modified="2013-09-15 16:10:20" minute="10" period="1" second="12" team="Southampton" time="10" type="save made" type_id="10"/>
	<message comment="Daniel Osvaldo has attempt saved (Low to the centre, 18-yard box, Big Chance, Right footed, Open play)" last_modified="2013-09-15 16:10:20" minute="10" period="1" second="12" team="West Ham" time="10" type="attempt blocked" type_id="15"/>
	<message comment="Ravel Morrison blocks a shot" last_modified="2013-09-15 16:09:36" minute="9" period="1" second="28" team="Southampton" time="9" type="save made" type_id="10"/>
	<message comment="Jay Rodriguez has shot blocked (Out of box, Right footed, Open play)" last_modified="2013-09-15 16:09:36" minute="9" period="1" second="28" team="West Ham" time="9" type="attempt blocked" type_id="15"/>
	<message comment="Formation Set" last_modified="2013-09-15 16:00:08" minute="0" period="14" second="0" team="West Ham" time="7" type="end" type_id="30"/>
	<message comment="Mark Noble wins a corner (To the left)" last_modified="2013-09-15 16:06:25" minute="6" period="1" second="17" team="Southampton" time="6" type="corner" type_id="6"/>
	<message comment="Mohamed Diamé has attempt saved (High to the right, 18-yard box, Right footed, Open play)" last_modified="2013-09-15 16:06:18" minute="6" period="1" second="10" team="Southampton" time="6" type="attempt blocked" type_id="15"/>
	<message comment="Artur Boruc makes a save (Standing, Parried into danger)" last_modified="2013-09-15 16:06:18" minute="6" period="1" second="10" team="West Ham" time="6" type="save made" type_id="10"/>
	<message comment="First half begins!" last_modified="2013-09-15 16:00:08" minute="0" period="1" second="0" team="West Ham" time="0" type="start" type_id="32"/>
</Commentary>
