<?xml version="1.0" ?>
<Commentary away_team_name="Crystal Palace" competition="English Premier League" game_date="2013-08-31" home_team_name="Sunderland" lang_id="en" season="Season 2013/2014" season_id="2013" sport_id="1" sport_name="Football">
	<message comment="Second half ends" minute="94" period="2" second="12" time="96" type="end" type_id="30"/>
	<message comment="GOAL! Stuart O'Keefe scores  (High to the left, Out of box, Left footed, Open play)" minute="91" period="2" second="22" time="93" type="goal scored" type_id="16"/>
	<message comment="Kagisho Dikgacoi wins a corner (To the left)" minute="88" period="2" second="19" time="90" type="corner" type_id="6"/>
	<message comment="Keiren Westwood makes a save (Diving)" minute="88" period="2" second="16" time="90" type="save made" type_id="10"/>
	<message comment="Kagisho Dikgacoi has attempt saved (High to the centre, Out of box, Right footed, Open play)" minute="88" period="2" second="16" time="90" type="attempt blocked" type_id="15"/>
	<message comment="Keiren Westwood makes a save (Parried safe)" minute="84" period="2" second="10" time="86" type="save made" type_id="10"/>
	<message comment="Jonathan Williams has attempt saved (Low to the left, 18-yard box, Right footed, Throw-in)" minute="84" period="2" second="10" time="86" type="attempt blocked" type_id="15"/>
	<message comment="Keiren Westwood makes a save (Diving, Parried into danger)" minute="83" period="2" second="41" time="85" type="save made" type_id="10"/>
	<message comment="Jonathan Williams has attempt saved (Low to the centre, 18-yard box, Left footed, Open play)" minute="83" period="2" second="41" time="85" type="attempt blocked" type_id="15"/>
	<message comment="Dwight Gayle is substituted off" minute="82" period="2" second="52" time="84" type="substitution off" type_id="18"/>
	<message comment="Aaron Wilbraham is substituted on" minute="82" period="2" second="52" time="84" type="substitution on" type_id="19"/>
	<message comment="Marouane Chamakh is substituted off" minute="82" period="2" second="36" time="84" type="substitution off" type_id="18"/>
	<message comment="Stuart O'Keefe is substituted on" minute="82" period="2" second="36" time="84" type="substitution on" type_id="19"/>
	<message comment="Adam Johnson has attempt saved (Low to the right, Out of box, Left footed, Open play)" minute="81" period="2" second="25" time="83" type="attempt blocked" type_id="15"/>
	<message comment="Julian Speroni makes a save (Collected, Diving)" minute="81" period="2" second="25" time="83" type="save made" type_id="10"/>
	<message comment="GOAL! Dwight Gayle scores  (Low to the centre, 18-yard box, Penalty, Big Chance, Right footed)" minute="78" period="2" second="43" time="80" type="goal scored" type_id="16"/>
	<message comment="John O'Shea recieves a red card" minute="77" period="2" second="45" time="79" type="card received" type_id="17"/>
	<message comment="Modibo Diakité wins a corner (To the left)" minute="74" period="2" second="4" time="76" type="corner" type_id="6"/>
	<message comment="Jonathan Williams misses attempt (To the left, Out of box, Left footed, Open play)" minute="70" period="2" second="44" time="72" type="attempt missed" type_id="13"/>
	<message comment="Adam Johnson wins a corner (To the right)" minute="67" period="2" second="58" time="69" type="corner" type_id="6"/>
	<message comment="Dean Moxey misses attempt (High to the right, Out of box, Left footed, Open play)" minute="66" period="2" second="21" time="68" type="attempt missed" type_id="13"/>
	<message comment="GOAL! Steven Fletcher scores , Assisted by Jack Colback (Low to the left, 18-yard box, Head, Open play)" minute="63" period="2" second="48" time="65" type="goal scored" type_id="16"/>
	<message comment="Jason Puncheon misses attempt (To the left, 18-yard box, Left footed, Open play)" minute="60" period="2" second="30" time="62" type="attempt missed" type_id="13"/>
	<message comment="Charalampos Mavrias is substituted on" minute="60" period="2" second="8" time="62" type="substitution on" type_id="19"/>
	<message comment="Emanuele Giaccherini is substituted off" minute="60" period="2" second="8" time="62" type="substitution off" type_id="18"/>
	<message comment="Joel Ward wins a corner (To the left)" minute="57" period="2" second="47" time="59" type="corner" type_id="6"/>
	<message comment="Dwight Gayle wins a corner (To the left)" minute="56" period="2" second="50" time="58" type="corner" type_id="6"/>
	<message comment="Modibo Diakité blocks a shot" minute="56" period="2" second="48" time="58" type="save made" type_id="10"/>
	<message comment="Dwight Gayle has shot blocked (18-yard box, Left footed, Open play)" minute="56" period="2" second="48" time="58" type="attempt blocked" type_id="15"/>
	<message comment="Mile Jedinak misses attempt (Out of box, Right footed, Fast break)" minute="55" period="2" second="45" time="57" type="attempt missed" type_id="13"/>
	<message comment="José Campaña is substituted off" minute="53" period="2" second="17" time="55" type="substitution off" type_id="18"/>
	<message comment="Jonathan Williams is substituted on" minute="53" period="2" second="17" time="55" type="substitution on" type_id="19"/>
	<message comment="Marouane Chamakh is caught offside" minute="52" period="2" time="54" type="offside" type_id="10000"/>
	<message comment="Joel Ward wins a corner (To the right)" minute="50" period="2" second="55" time="52" type="corner" type_id="6"/>
	<message comment="Steven Fletcher is caught offside" minute="50" period="2" time="52" type="offside" type_id="10000"/>
	<message comment="Sebastian Larsson wins a corner (To the right)" minute="45" period="2" second="51" time="47" type="corner" type_id="6"/>
	<message comment="Dong-Won Ji is substituted off" minute="45" period="2" second="0" time="47" type="substitution off" type_id="18"/>
	<message comment="Steven Fletcher is substituted on" minute="45" period="2" second="0" time="47" type="substitution on" type_id="19"/>
	<message comment="Second half begins!" minute="45" period="2" second="0" time="47" type="start" type_id="32"/>
	<message comment="First half ends" minute="46" period="1" second="7" time="46" type="end" type_id="30"/>
	<message comment="Danny Gabbidon blocks a shot" minute="43" period="1" second="11" time="43" type="save made" type_id="10"/>
	<message comment="Emanuele Giaccherini has shot blocked (Out of box, Right footed, Open play)" minute="43" period="1" second="11" time="43" type="attempt blocked" type_id="15"/>
	<message comment="Mile Jedinak misses attempt (Out of box, Right footed, Fast break)" minute="41" period="1" second="45" time="41" type="attempt missed" type_id="13"/>
	<message comment="Adam Johnson has shot blocked (Out of box, Left footed, Free kick)" minute="40" period="1" second="54" time="40" type="attempt blocked" type_id="15"/>
	<message comment="Dean Moxey blocks a shot" minute="40" period="1" second="54" time="40" type="save made" type_id="10"/>
	<message comment="José Campaña wins a corner (To the right)" minute="39" period="1" second="8" time="39" type="corner" type_id="6"/>
	<message comment="Modibo Diakité blocks a shot" minute="36" period="1" second="27" time="36" type="save made" type_id="10"/>
	<message comment="Dwight Gayle has shot blocked (Out of box, Left footed, Open play)" minute="36" period="1" second="27" time="36" type="attempt blocked" type_id="15"/>
	<message comment="Jason Puncheon misses attempt (Out of box, Left footed, Fast break)" minute="34" period="1" second="45" time="34" type="attempt missed" type_id="13"/>
	<message comment="Kagisho Dikgacoi misses attempt (High to the right, Out of box, Right footed, Open play)" minute="32" period="1" second="55" time="32" type="attempt missed" type_id="13"/>
	<message comment="Emanuele Giaccherini wins a corner (To the left)" minute="30" period="1" second="49" time="30" type="corner" type_id="6"/>
	<message comment="Emanuele Giaccherini has shot blocked (18-yard box, Right footed, Open play)" minute="30" period="1" second="46" time="30" type="attempt blocked" type_id="15"/>
	<message comment="Danny Gabbidon blocks a shot" minute="30" period="1" second="46" time="30" type="save made" type_id="10"/>
	<message comment="Connor Wickham has shot blocked (18-yard box, Right footed, Open play)" minute="29" period="1" second="56" time="29" type="attempt blocked" type_id="15"/>
	<message comment="Danny Gabbidon blocks a shot" minute="29" period="1" second="56" time="29" type="save made" type_id="10"/>
	<message comment="Jason Puncheon misses attempt (Out of box, Left footed, Fast break)" minute="25" period="1" second="9" time="25" type="attempt missed" type_id="13"/>
	<message comment="Damien Delaney recieves a yellow card" minute="24" period="1" second="20" time="24" type="card received" type_id="17"/>
	<message comment="Dean Moxey is caught offside" minute="24" period="1" time="24" type="offside" type_id="10000"/>
	<message comment="Kagisho Dikgacoi has shot blocked (Out of box, Right footed, Open play)" minute="23" period="1" second="59" time="23" type="attempt blocked" type_id="15"/>
	<message comment="David Vaughan blocks a shot" minute="23" period="1" second="59" time="23" type="save made" type_id="10"/>
	<message comment="Connor Wickham misses attempt (To the right, 18-yard box, Left footed, Open play)" minute="22" period="1" second="43" time="22" type="attempt missed" type_id="13"/>
	<message comment="Modibo Diakité misses attempt (High to the right, 18-yard box, Head, From corner)" minute="20" period="1" second="45" time="20" type="attempt missed" type_id="13"/>
	<message comment="Ondrej Celustka wins a corner (To the left)" minute="20" period="1" second="14" time="20" type="corner" type_id="6"/>
	<message comment="Adam Johnson wins a corner (To the right)" minute="16" period="1" second="17" time="16" type="corner" type_id="6"/>
	<message comment="Sebastian Larsson has shot blocked (18-yard box, Left footed, Open play)" minute="10" period="1" second="49" time="10" type="attempt blocked" type_id="15"/>
	<message comment="Kagisho Dikgacoi blocks a shot" minute="10" period="1" second="49" time="10" type="save made" type_id="10"/>
	<message comment="Damien Delaney blocks a shot" minute="10" period="1" second="47" time="10" type="save made" type_id="10"/>
	<message comment="Connor Wickham has shot blocked (6-yard box, Right footed, Open play)" minute="10" period="1" second="47" time="10" type="attempt blocked" type_id="15"/>
	<message comment="GOAL! Danny Gabbidon scores  (Low to the centre, 6-yard box, Left footed, From corner)" minute="8" period="1" second="33" time="8" type="goal scored" type_id="16"/>
	<message comment="Joel Ward wins a corner (To the left)" minute="8" period="1" second="8" time="8" type="corner" type_id="6"/>
	<message comment="Keiren Westwood makes a save (Diving, Collected)" minute="7" period="1" second="16" time="7" type="save made" type_id="10"/>
	<message comment="José Campaña has attempt saved (Low to the left, Out of box, Right footed, Open play)" minute="7" period="1" second="16" time="7" type="attempt blocked" type_id="15"/>
	<message comment="Formation Set" minute="0" period="14" second="0" time="6" type="end" type_id="30"/>
	<message comment="First half begins!" minute="0" period="1" second="0" time="0" type="start" type_id="32"/>
</Commentary>
