<?xml version="1.0" ?>
<Commentary away_team_name="Sunderland" competition="English Premier League" game_date="2012-10-21" home_team_name="Newcastle United" lang_id="en" season="Season 2012/2013" season_id="2012" sport_id="1" sport_name="Football">
	<message comment="Second half ends" minute="94" period="2" second="12" time="98" type="end" type_id="30"/>
	<message comment="Davide Santon blocks a shot" minute="93" period="2" second="28" time="97" type="save made" type_id="10"/>
	<message comment="Louis Saha has shot blocked (18-yard box, Left footed, Open play)" minute="93" period="2" second="28" time="97" type="attempt blocked" type_id="15"/>
	<message comment="Craig Gardner wins a corner (To the right)" minute="91" period="2" second="2" time="95" type="corner" type_id="6"/>
	<message comment="Jonás Gutiérrez blocks a shot" minute="91" period="2" second="0" time="95" type="save made" type_id="10"/>
	<message comment="Craig Gardner has shot blocked (Out of box, Right footed, Open play)" minute="91" period="2" second="0" time="95" type="attempt blocked" type_id="15"/>
	<message comment="Steven Taylor wins a corner (To the right)" minute="89" period="2" second="53" time="93" type="corner" type_id="6"/>
	<message comment="James McClean misses attempt (Out of box, Right footed, Open play)" minute="88" period="2" second="22" time="92" type="attempt missed" type_id="13"/>
	<message comment="Mike Williamson blocks a shot" minute="88" period="2" second="20" time="92" type="save made" type_id="10"/>
	<message comment="Louis Saha has shot blocked (18-yard box, Right footed, Open play)" minute="88" period="2" second="20" time="92" type="attempt blocked" type_id="15"/>
	<message comment="Yohan Cabaye recieves a yellow card" minute="85" period="2" second="31" time="89" type="card received" type_id="17"/>
	<message comment="Demba Ba scores an OWN GOAL!  (Low to the right, 18-yard box, Head, Set piece)" minute="84" period="2" second="29" time="88" type="goal scored" type_id="16"/>
	<message comment="John O'Shea misses attempt (To the left, 18-yard box, Head, Set piece)" minute="84" period="2" second="28" time="88" type="attempt missed" type_id="13"/>
	<message comment="Mike Williamson recieves a yellow card" minute="83" period="2" second="46" time="87" type="card received" type_id="17"/>
	<message comment="Hatem Ben Arfa is substituted off" minute="83" period="2" second="8" time="87" type="substitution off" type_id="18"/>
	<message comment="Gabriel Obertan is substituted on" minute="83" period="2" second="8" time="87" type="substitution on" type_id="19"/>
	<message comment="Adam Johnson is substituted off" minute="82" period="2" second="25" time="86" type="substitution off" type_id="18"/>
	<message comment="David Vaughan is substituted on" minute="82" period="2" second="25" time="86" type="substitution on" type_id="19"/>
	<message comment="Louis Saha misses attempt (6-yard box, Right footed, From corner)" minute="81" period="2" second="49" time="85" type="attempt missed" type_id="13"/>
	<message comment="James McClean wins a corner (To the left)" minute="81" period="2" second="23" time="85" type="corner" type_id="6"/>
	<message comment="Jonás Gutiérrez blocks a shot" minute="80" period="2" second="45" time="84" type="save made" type_id="10"/>
	<message comment="Adam Johnson has shot blocked (Out of box, Left footed, Open play)" minute="80" period="2" second="45" time="84" type="attempt blocked" type_id="15"/>
	<message comment="John O'Shea blocks a shot" minute="80" period="2" second="20" time="84" type="save made" type_id="10"/>
	<message comment="Demba Ba has shot blocked (18-yard box, Right footed, Open play)" minute="80" period="2" second="20" time="84" type="attempt blocked" type_id="15"/>
	<message comment="Fabricio Coloccini is substituted off" minute="79" period="2" second="25" time="83" type="substitution off" type_id="18"/>
	<message comment="Steven Taylor is substituted on" minute="79" period="2" second="25" time="83" type="substitution on" type_id="19"/>
	<message comment="James Perch blocks a shot (Last line)" minute="77" period="2" second="59" time="81" type="save made" type_id="10"/>
	<message comment="Carlos Cuellar has shot blocked (18-yard box, Right footed, From corner)" minute="77" period="2" second="59" time="81" type="attempt blocked" type_id="15"/>
	<message comment="James McClean wins a corner (To the left)" minute="77" period="2" second="32" time="81" type="corner" type_id="6"/>
	<message comment="Louis Saha misses attempt (High, 18-yard box, Head, From corner)" minute="74" period="2" second="28" time="78" type="attempt missed" type_id="13"/>
	<message comment="Craig Gardner wins a corner (To the right)" minute="74" period="2" second="10" time="78" type="corner" type_id="6"/>
	<message comment="James Perch blocks a shot" minute="74" period="2" second="8" time="78" type="save made" type_id="10"/>
	<message comment="Craig Gardner has shot blocked (Out of box, Right footed, Open play)" minute="74" period="2" second="8" time="78" type="attempt blocked" type_id="15"/>
	<message comment="Simon Mignolet makes a save (Standing, Parried into danger, Feet)" minute="73" period="2" second="34" time="77" type="save made" type_id="10"/>
	<message comment="Demba Ba has attempt saved (Low to the centre, 18-yard box, Big Chance, Right footed, Open play)" minute="73" period="2" second="34" time="77" type="attempt blocked" type_id="15"/>
	<message comment="Sebastian Larsson misses attempt (Out of box, Right footed, Free kick)" minute="68" period="2" second="48" time="72" type="attempt missed" type_id="13"/>
	<message comment="Fabricio Coloccini recieves a yellow card" minute="67" period="2" second="57" time="71" type="card received" type_id="17"/>
	<message comment="Stéphane Sessegnon is substituted off" minute="64" period="2" second="20" time="68" type="substitution off" type_id="18"/>
	<message comment="Louis Saha is substituted on" minute="64" period="2" second="20" time="68" type="substitution on" type_id="19"/>
	<message comment="James McClean wins a corner (To the left)" minute="63" period="2" second="42" time="67" type="corner" type_id="6"/>
	<message comment="James McClean misses attempt (To the right, Out of box, Left footed, Open play)" minute="63" period="2" second="40" time="67" type="attempt missed" type_id="13"/>
	<message comment="Stéphane Sessegnon is caught offside" minute="52" period="2" time="56" type="offside" type_id="10000"/>
	<message comment="Demba Ba has attempt saved (High to the left, Out of box, Right footed, Open play)" minute="47" period="2" second="8" time="51" type="attempt blocked" type_id="15"/>
	<message comment="Simon Mignolet makes a save (Standing)" minute="47" period="2" second="8" time="51" type="save made" type_id="10"/>
	<message comment="Steven Fletcher misses attempt (To the left, 18-yard box, Head, Open play)" minute="46" period="2" second="24" time="50" type="attempt missed" type_id="13"/>
	<message comment="Second half begins!" minute="45" period="2" second="0" time="49" type="start" type_id="32"/>
	<message comment="First half ends" minute="48" period="1" second="8" time="48" type="end" type_id="30"/>
	<message comment="James McClean wins a corner (To the right)" minute="46" period="1" second="31" time="46" type="corner" type_id="6"/>
	<message comment="Fabricio Coloccini blocks a shot" minute="46" period="1" second="30" time="46" type="save made" type_id="10"/>
	<message comment="James McClean has shot blocked (Out of box, Left footed, Open play)" minute="46" period="1" second="30" time="46" type="attempt blocked" type_id="15"/>
	<message comment="Steven Fletcher is caught offside" minute="45" period="1" time="45" type="offside" type_id="10000"/>
	<message comment="Craig Gardner misses attempt (To the right, Out of box, Right footed, Open play)" minute="42" period="1" second="10" time="42" type="attempt missed" type_id="13"/>
	<message comment="Demba Ba misses attempt (High, 18-yard box, Big Chance, Right footed, From corner)" minute="40" period="1" second="35" time="40" type="attempt missed" type_id="13"/>
	<message comment="Fabricio Coloccini has shot blocked (Out of box, Right footed, From corner)" minute="40" period="1" second="33" time="40" type="attempt blocked" type_id="15"/>
	<message comment="Carlos Cuellar blocks a shot" minute="40" period="1" second="33" time="40" type="save made" type_id="10"/>
	<message comment="Tim Krul wins a corner (To the right)" minute="39" period="1" second="57" time="39" type="corner" type_id="6"/>
	<message comment="Shola Ameobi is substituted off" minute="38" period="1" second="9" time="38" type="substitution off" type_id="18"/>
	<message comment="James Perch is substituted on" minute="38" period="1" second="9" time="38" type="substitution on" type_id="19"/>
	<message comment="Craig Gardner wins a corner (To the left)" minute="37" period="1" second="1" time="37" type="corner" type_id="6"/>
	<message comment="Mike Williamson blocks a shot" minute="36" period="1" second="58" time="36" type="save made" type_id="10"/>
	<message comment="Craig Gardner has shot blocked (Out of box, Right footed, Set piece)" minute="36" period="1" second="58" time="36" type="attempt blocked" type_id="15"/>
	<message comment="Craig Gardner wins a corner (To the right)" minute="35" period="1" second="41" time="35" type="corner" type_id="6"/>
	<message comment="Craig Gardner misses attempt (Out of box, Right footed, Free kick)" minute="34" period="1" second="22" time="34" type="attempt missed" type_id="13"/>
	<message comment="Adam Johnson misses attempt (High to the left, 18-yard box, Left footed, Open play)" minute="31" period="1" second="55" time="31" type="attempt missed" type_id="13"/>
	<message comment="Jack Colback has shot blocked (18-yard box, Left footed, Open play)" minute="31" period="1" second="52" time="31" type="attempt blocked" type_id="15"/>
	<message comment="Mike Williamson blocks a shot" minute="31" period="1" second="52" time="31" type="save made" type_id="10"/>
	<message comment="Craig Gardner blocks a shot" minute="29" period="1" second="18" time="29" type="save made" type_id="10"/>
	<message comment="Demba Ba has shot blocked (Out of box, Right footed, Open play)" minute="29" period="1" second="18" time="29" type="attempt blocked" type_id="15"/>
	<message comment="Shola Ameobi recieves a yellow card" minute="24" period="1" second="12" time="24" type="card received" type_id="17"/>
	<message comment="Cheick Tioté recieves a red card" minute="24" period="1" second="5" time="24" type="card received" type_id="17"/>
	<message comment="Yohan Cabaye wins a corner (To the left)" minute="20" period="1" second="28" time="20" type="corner" type_id="6"/>
	<message comment="Yohan Cabaye has attempt saved (High to the left, Out of box, Right footed, Free kick)" minute="20" period="1" second="26" time="20" type="attempt blocked" type_id="15"/>
	<message comment="Simon Mignolet makes a save (Parried safe)" minute="20" period="1" second="26" time="20" type="save made" type_id="10"/>
	<message comment="Demba Ba has shot blocked (18-yard box, Left footed, Open play)" minute="17" period="1" second="0" time="17" type="attempt blocked" type_id="15"/>
	<message comment="Carlos Cuellar blocks a shot" minute="17" period="1" second="0" time="17" type="save made" type_id="10"/>
	<message comment="Demba Ba has shot blocked (18-yard box, Head, Open play)" minute="16" period="1" second="59" time="16" type="attempt blocked" type_id="15"/>
	<message comment="John O'Shea blocks a shot" minute="16" period="1" second="59" time="16" type="save made" type_id="10"/>
	<message comment="Tim Krul makes a save (Collected)" minute="16" period="1" second="19" time="16" type="save made" type_id="10"/>
	<message comment="Sebastian Larsson has attempt saved (Low to the left, Out of box, Right footed, Free kick)" minute="16" period="1" second="19" time="16" type="attempt blocked" type_id="15"/>
	<message comment="Cheick Tioté blocks a shot" minute="8" period="1" second="3" time="8" type="save made" type_id="10"/>
	<message comment="Stéphane Sessegnon has shot blocked (Out of box, Left footed, Open play)" minute="8" period="1" second="3" time="8" type="attempt blocked" type_id="15"/>
	<message comment="Steven Fletcher is caught offside" minute="8" period="1" time="8" type="offside" type_id="10000"/>
	<message comment="Formation Set" minute="0" period="14" second="0" time="8" type="end" type_id="30"/>
	<message comment="GOAL! Yohan Cabaye scores  (Low to the left, 18-yard box, Big Chance, Right footed, Open play)" minute="2" period="1" second="10" time="2" type="goal scored" type_id="16"/>
	<message comment="Simon Mignolet makes a save (Parried into danger, Feet)" minute="2" period="1" second="7" time="2" type="save made" type_id="10"/>
	<message comment="Demba Ba has attempt saved (Low to the centre, 18-yard box, Right footed, Open play)" minute="2" period="1" second="7" time="2" type="attempt blocked" type_id="15"/>
	<message comment="Jonás Gutiérrez wins a corner (To the left)" minute="0" period="1" second="29" time="0" type="corner" type_id="6"/>
	<message comment="First half begins!" minute="0" period="1" second="0" time="0" type="start" type_id="32"/>
</Commentary>
